{
    "structure": {
        "readme": "ddh-intro.md"
    },
    "variables": {
        "slackURL": "https://quackslack.herokuapp.com",
        "forumURL": "https://forum.duckduckhack.com",
        "meetupURL": "http://www.meetup.com/pro/duckduckgo/",
        "twitterURL": "https://twitter.com/duckduckhack/",
        "email": "open@duckduckgo.com"
    },
    "plugins": ["anchorjs"],
    "pluginsConfig": {
        "anchorjs": {
            "icon": "#",
            "placement": "left",
            "visible": "always"
        }
    }
}
